{
  "name": "TicketingSystem",
  "fields": [
    {
      "fieldName": "url",
      "fieldType": "String",
      "fieldValidateRules": [
        "required"
      ]
    },
    {
      "fieldName": "serviceAccount",
      "fieldType": "String",
      "fieldValidateRules": [
        "required"
      ]
    },
    {
      "fieldName": "serviceAccountSecret",
      "fieldType": "String",
      "fieldValidateRules": [
        "required"
      ]
    },
    {
      "fieldName": "systemId",
      "fieldType": "String"
    }
  ],
  "relationships": [],
  "changelogDate": "20210223144908",
  "entityTableName": "ticketing_system",
  "dto": "no",
  "pagination": "no",
  "service": "serviceImpl",
  "jpaMetamodelFiltering": false,
  "fluentMethods": true,
  "readOnly": false,
  "embedded": false,
  "clientRootFolder": "custportApp",
  "applications": "*",
  "microserviceName": "custportApp"
}
